pyfastchem.cpython-37m-x86_64-linux-gnu.so
pyfastchem.libs/libgcc_s-a3a07607.so.1
pyfastchem.libs/libstdc++-496613c0.so.6.0.32
pyfastchem.libs/libgomp-1f0f45f5.so.1.0.0
pyfastchem-3.1.3.dist-info/METADATA
pyfastchem-3.1.3.dist-info/RECORD
pyfastchem-3.1.3.dist-info/top_level.txt
pyfastchem-3.1.3.dist-info/WHEEL
