Metadata-Version: 2.1
Name: pyfastchem
Version: 3.1.3
Summary: FastChem, an ultra-fast equilibrium chemistry
Home-page: https://github.com/NewStrangeWorlds/FastChem
Author: Daniel Kitzmann, Joachim Stock, Brett Morris
License: GPL 3.0
License-File: licence.md
